{"assets/fonts/Poppins-Bold.ttf":["assets/fonts/Poppins-Bold.ttf"],"assets/fonts/Poppins-Regular.ttf":["assets/fonts/Poppins-Regular.ttf"],"assets/fonts/Poppins-SemiBold.ttf":["assets/fonts/Poppins-SemiBold.ttf"],"assets/images/1.jpeg":["assets/images/1.jpeg"],"assets/images/10.jpeg":["assets/images/10.jpeg"],"assets/images/11.jpeg":["assets/images/11.jpeg"],"assets/images/13.png":["assets/images/13.png"],"assets/images/14.png":["assets/images/14.png"],"assets/images/2.jpeg":["assets/images/2.jpeg"],"assets/images/3.jpeg":["assets/images/3.jpeg"],"assets/images/4.jpeg":["assets/images/4.jpeg"],"assets/images/5.jpeg":["assets/images/5.jpeg"],"assets/images/6.jpeg":["assets/images/6.jpeg"],"assets/images/7.jpeg":["assets/images/7.jpeg"],"assets/images/8.jpeg":["assets/images/8.jpeg"],"assets/images/9.jpeg":["assets/images/9.jpeg"],"assets/images/android.svg":["assets/images/android.svg"],"assets/images/dev_img.jpeg":["assets/images/dev_img.jpeg"],"assets/images/dev_img.png":["assets/images/dev_img.png"],"assets/images/portfolio_icon.png":["assets/images/portfolio_icon.png"],"assets/images/ruler.svg":["assets/images/ruler.svg"],"assets/images/slider.svg":["assets/images/slider.svg"],"packages/cupertino_icons/assets/CupertinoIcons.ttf":["packages/cupertino_icons/assets/CupertinoIcons.ttf"],"packages/font_awesome_flutter/lib/fonts/fa-brands-400.ttf":["packages/font_awesome_flutter/lib/fonts/fa-brands-400.ttf"],"packages/font_awesome_flutter/lib/fonts/fa-regular-400.ttf":["packages/font_awesome_flutter/lib/fonts/fa-regular-400.ttf"],"packages/font_awesome_flutter/lib/fonts/fa-solid-900.ttf":["packages/font_awesome_flutter/lib/fonts/fa-solid-900.ttf"]}